plover_russian_trillo/__init__.py
plover_russian_trillo/system.py
plover_russian_trillo/dictionaries/trillo_prefixes.json
plover_russian_trillo/dictionaries/trillo_roots.json
plover_russian_trillo/dictionaries/trillo_suffixes.json
plover_russian_trillo/dictionaries/trillo_user.json
plover_russian_trillo-0.0.2.dist-info/METADATA
plover_russian_trillo-0.0.2.dist-info/WHEEL
plover_russian_trillo-0.0.2.dist-info/entry_points.txt
plover_russian_trillo-0.0.2.dist-info/top_level.txt
plover_russian_trillo-0.0.2.dist-info/zip-safe
plover_russian_trillo-0.0.2.dist-info/RECORD
